securepay/__init__.py
securepay/securepay.py
securepay-1.0.0.dist-info/COPYING
securepay-1.0.0.dist-info/METADATA
securepay-1.0.0.dist-info/WHEEL
securepay-1.0.0.dist-info/top_level.txt
securepay-1.0.0.dist-info/RECORD
