Metadata-Version: 2.1
Name: securepay
Version: 1.0.0
Summary: Interface to the Securepay credit card gateway.
Home-page: https://github.com/BenSturmfels/python-securepay
Author: Ben Sturmfels
Author-email: ben@sturm.com.au
License: UNKNOWN
Project-URL: Source, https://github.com/BenSturmfels/python-securepay
Project-URL: Bug Reports, https://github.com/BenSturmfels/python-securepay/issues
Platform: UNKNOWN
Classifier: Development Status :: 5 - Production/Stable
Classifier: Intended Audience :: Developers
Classifier: Topic :: Office/Business :: Financial
Classifier: License :: OSI Approved :: Apache Software License
Classifier: Programming Language :: Python :: 3
Requires-Python: >=3.6
Requires-Dist: lxml (>=3.3.3)
